fluigi_monitor/__init__.py
fluigi_monitor/fluigi_monitor.py
fluigi_monitor/luigi_monitor.py
fluigi_monitor-1.1.5.dist-info/METADATA
fluigi_monitor-1.1.5.dist-info/WHEEL
fluigi_monitor-1.1.5.dist-info/entry_points.txt
fluigi_monitor-1.1.5.dist-info/top_level.txt
fluigi_monitor-1.1.5.dist-info/RECORD
