Metadata-Version: 2.1
Name: fluigi-monitor
Version: 1.1.5
Summary: Send summary messages of your Luigi jobs to Slack.
Home-page: https://github.com/Foristkirito/luigi-monitor
Author: Hudl
Author-email: xiaxin0202@foxmail.com
License: MIT
Keywords: luigi
Platform: UNKNOWN
Classifier: Development Status :: 3 - Alpha
Classifier: Intended Audience :: Developers
Classifier: License :: OSI Approved :: MIT License
Classifier: Programming Language :: Python :: 2.7
Classifier: Programming Language :: Python :: 3.6
Classifier: Programming Language :: Python :: 3.7
Requires-Dist: requests
Requires-Dist: luigi
